{"observations":[{"stationID":"ISTGBUCH2","tz":"Europe/London","obsTimeUtc":"2022-04-24T23:59:51Z","obsTimeLocal":"2022-04-25 00:59:51","epoch":1650844791,"lat":56.118,"lon":-4.301648,"solarRadiationHigh":0.00,"uvHigh":0.0,"winddirAvg":84,"humidityHigh":89,"humidityLow":85,"humidityAvg":87,"qcStatus":1,"metric":{"tempHigh":8,"tempLow":7,"tempAvg":7,"windspeedHigh":4,"windspeedLow":0,"windspeedAvg":1,"windgustHigh":5,"windgustLow":0,"windgustAvg":2,"dewptHigh":6,"dewptLow":5,"dewptAvg":5,"windchillHigh":8,"windchillLow":7,"windchillAvg":7,"heatindexHigh":8,"heatindexLow":7,"heatindexAvg":7,"pressureMax":1016.22,"pressureMin":1015.82,"pressureTrend":0.00,"precipRate":0.00,"precipTotal":0.00}},{"stationID":"ISTGBUCH2","tz":"Europe/London","obsTimeUtc":"2022-04-25T00:59:51Z","obsTimeLocal":"2022-04-25 01:59:51","epoch":1650848391,"lat":56.118,"lon":-4.301648,"solarRadiationHigh":0.00,"uvHigh":0.0,"winddirAvg":94,"humidityHigh":87,"humidityLow":80,"humidityAvg":83,"qcStatus":1,"metric":{"tempHigh":7,"tempLow":7,"tempAvg":7,"windspeedHigh":7,"windspeedLow":0,"windspeedAvg":3,"windgustHigh":9,"windgustLow":0,"windgustAvg":3,"dewptHigh":5,"dewptLow":4,"dewptAvg":5,"windchillHigh":7,"windchillLow":6,"windchillAvg":7,"heatindexHigh":7,"heatindexLow":7,"heatindexAvg":7,"pressureMax":1016.32,"pressureMin":1015.82,"pressureTrend":-0.20,"precipRate":0.00,"precipTotal":0.00}},{"stationID":"ISTGBUCH2","tz":"Europe/London","obsTimeUtc":"2022-04-25T01:59:51Z","obsTimeLocal":"2022-04-25 02:59:51","epoch":1650851991,"lat":56.118,"lon":-4.301648,"solarRadiationHigh":0.00,"uvHigh":0.0,"winddirAvg":93,"humidityHigh":83,"humidityLow":81,"humidityAvg":82,"qcStatus":1,"metric":{"tempHigh":7,"tempLow":7,"tempAvg":7,"windspeedHigh":5,"windspeedLow":1,"windspeedAvg":2,"windgustHigh":7,"windgustLow":2,"windgustAvg":3,"dewptHigh":4,"dewptLow":4,"dewptAvg":4,"windchillHigh":7,"windchillLow":7,"windchillAvg":7,"heatindexHigh":7,"heatindexLow":7,"heatindexAvg":7,"pressureMax":1016.02,"pressureMin":1015.51,"pressureTrend":0.00,"precipRate":0.00,"precipTotal":0.00}},{"stationID":"ISTGBUCH2","tz":"Europe/London","obsTimeUtc":"2022-04-25T02:59:51Z","obsTimeLocal":"2022-04-25 03:59:51","epoch":1650855591,"lat":56.118,"lon":-4.301648,"solarRadiationHigh":0.00,"uvHigh":0.0,"winddirAvg":96,"humidityHigh":85,"humidityLow":82,"humidityAvg":83,"qcStatus":1,"metric":{"tempHigh":7,"tempLow":7,"tempAvg":7,"windspeedHigh":4,"windspeedLow":0,"windspeedAvg":1,"windgustHigh":4,"windgustLow":0,"windgustAvg":1,"dewptHigh":4,"dewptLow":4,"dewptAvg":4,"windchillHigh":7,"windchillLow":7,"windchillAvg":7,"heatindexHigh":7,"heatindexLow":7,"heatindexAvg":7,"pressureMax":1015.92,"pressureMin":1015.34,"pressureTrend":-0.20,"precipRate":0.00,"precipTotal":0.00}},{"stationID":"ISTGBUCH2","tz":"Europe/London","obsTimeUtc":"2022-04-25T03:59:51Z","obsTimeLocal":"2022-04-25 04:59:51","epoch":1650859191,"lat":56.118,"lon":-4.301648,"solarRadiationHigh":0.00,"uvHigh":0.0,"winddirAvg":100,"humidityHigh":85,"humidityLow":82,"humidityAvg":83,"qcStatus":1,"metric":{"tempHigh":7,"tempLow":7,"tempAvg":7,"windspeedHigh":4,"windspeedLow":0,"windspeedAvg":1,"windgustHigh":5,"windgustLow":0,"windgustAvg":2,"dewptHigh":4,"dewptLow":4,"dewptAvg":4,"windchillHigh":7,"windchillLow":7,"windchillAvg":7,"heatindexHigh":7,"heatindexLow":7,"heatindexAvg":7,"pressureMax":1015.71,"pressureMin":1015.34,"pressureTrend":-0.10,"precipRate":0.00,"precipTotal":0.00}},{"stationID":"ISTGBUCH2","tz":"Europe/London","obsTimeUtc":"2022-04-25T04:59:51Z","obsTimeLocal":"2022-04-25 05:59:51","epoch":1650862791,"lat":56.118,"lon":-4.301648,"solarRadiationHigh":0.36,"uvHigh":0.0,"winddirAvg":81,"humidityHigh":85,"humidityLow":82,"humidityAvg":83,"qcStatus":1,"metric":{"tempHigh":7,"tempLow":6,"tempAvg":6,"windspeedHigh":3,"windspeedLow":0,"windspeedAvg":0,"windgustHigh":4,"windgustLow":0,"windgustAvg":0,"dewptHigh":4,"dewptLow":3,"dewptAvg":4,"windchillHigh":7,"windchillLow":6,"windchillAvg":6,"heatindexHigh":7,"heatindexLow":6,"heatindexAvg":6,"pressureMax":1015.71,"pressureMin":1015.24,"pressureTrend":0.10,"precipRate":0.00,"precipTotal":0.00}},{"stationID":"ISTGBUCH2","tz":"Europe/London","obsTimeUtc":"2022-04-25T05:59:51Z","obsTimeLocal":"2022-04-25 06:59:51","epoch":1650866391,"lat":56.118,"lon":-4.301648,"solarRadiationHigh":38.53,"uvHigh":0.0,"winddirAvg":333,"humidityHigh":88,"humidityLow":84,"humidityAvg":86,"qcStatus":1,"metric":{"tempHigh":7,"tempLow":6,"tempAvg":6,"windspeedHigh":2,"windspeedLow":0,"windspeedAvg":0,"windgustHigh":2,"windgustLow":0,"windgustAvg":0,"dewptHigh":5,"dewptLow":4,"dewptAvg":4,"windchillHigh":7,"windchillLow":6,"windchillAvg":6,"heatindexHigh":7,"heatindexLow":6,"heatindexAvg":6,"pressureMax":1016.02,"pressureMin":1015.34,"pressureTrend":0.20,"precipRate":0.00,"precipTotal":0.00}},{"stationID":"ISTGBUCH2","tz":"Europe/London","obsTimeUtc":"2022-04-25T06:59:51Z","obsTimeLocal":"2022-04-25 07:59:51","epoch":1650869991,"lat":56.118,"lon":-4.301648,"solarRadiationHigh":101.41,"uvHigh":1.0,"winddirAvg":24,"humidityHigh":87,"humidityLow":83,"humidityAvg":85,"qcStatus":1,"metric":{"tempHigh":7,"tempLow":7,"tempAvg":7,"windspeedHigh":2,"windspeedLow":0,"windspeedAvg":0,"windgustHigh":2,"windgustLow":0,"windgustAvg":0,"dewptHigh":5,"dewptLow":4,"dewptAvg":5,"windchillHigh":7,"windchillLow":7,"windchillAvg":7,"heatindexHigh":7,"heatindexLow":7,"heatindexAvg":7,"pressureMax":1016.22,"pressureMin":1015.51,"pressureTrend":0.20,"precipRate":0.00,"precipTotal":0.00}},{"stationID":"ISTGBUCH2","tz":"Europe/London","obsTimeUtc":"2022-04-25T07:59:51Z","obsTimeLocal":"2022-04-25 08:59:51","epoch":1650873591,"lat":56.118,"lon":-4.301648,"solarRadiationHigh":172.61,"uvHigh":1.0,"winddirAvg":75,"humidityHigh":86,"humidityLow":82,"humidityAvg":84,"qcStatus":1,"metric":{"tempHigh":8,"tempLow":7,"tempAvg":8,"windspeedHigh":3,"windspeedLow":0,"windspeedAvg":1,"windgustHigh":4,"windgustLow":0,"windgustAvg":1,"dewptHigh":6,"dewptLow":4,"dewptAvg":5,"windchillHigh":8,"windchillLow":7,"windchillAvg":8,"heatindexHigh":8,"heatindexLow":7,"heatindexAvg":8,"pressureMax":1016.42,"pressureMin":1015.82,"pressureTrend":0.10,"precipRate":0.00,"precipTotal":0.00}},{"stationID":"ISTGBUCH2","tz":"Europe/London","obsTimeUtc":"2022-04-25T08:59:51Z","obsTimeLocal":"2022-04-25 09:59:51","epoch":1650877191,"lat":56.118,"lon":-4.301648,"solarRadiationHigh":315.75,"uvHigh":3.0,"winddirAvg":97,"humidityHigh":84,"humidityLow":79,"humidityAvg":81,"qcStatus":1,"metric":{"tempHigh":9,"tempLow":8,"tempAvg":9,"windspeedHigh":5,"windspeedLow":0,"windspeedAvg":2,"windgustHigh":7,"windgustLow":0,"windgustAvg":3,"dewptHigh":7,"dewptLow":5,"dewptAvg":6,"windchillHigh":9,"windchillLow":8,"windchillAvg":9,"heatindexHigh":9,"heatindexLow":8,"heatindexAvg":9,"pressureMax":1016.73,"pressureMin":1015.92,"pressureTrend":0.51,"precipRate":0.00,"precipTotal":0.00}},{"stationID":"ISTGBUCH2","tz":"Europe/London","obsTimeUtc":"2022-04-25T09:59:51Z","obsTimeLocal":"2022-04-25 10:59:51","epoch":1650880791,"lat":56.118,"lon":-4.301648,"solarRadiationHigh":642.02,"uvHigh":6.0,"winddirAvg":108,"humidityHigh":82,"humidityLow":76,"humidityAvg":79,"qcStatus":1,"metric":{"tempHigh":11,"tempLow":9,"tempAvg":10,"windspeedHigh":9,"windspeedLow":0,"windspeedAvg":4,"windgustHigh":11,"windgustLow":2,"windgustAvg":5,"dewptHigh":8,"dewptLow":6,"dewptAvg":7,"windchillHigh":11,"windchillLow":9,"windchillAvg":10,"heatindexHigh":11,"heatindexLow":9,"heatindexAvg":10,"pressureMax":1017.14,"pressureMin":1016.42,"pressureTrend":0.10,"precipRate":0.00,"precipTotal":0.00}},{"stationID":"ISTGBUCH2","tz":"Europe/London","obsTimeUtc":"2022-04-25T10:59:51Z","obsTimeLocal":"2022-04-25 11:59:51","epoch":1650884391,"lat":56.118,"lon":-4.301648,"solarRadiationHigh":673.21,"uvHigh":6.0,"winddirAvg":120,"humidityHigh":80,"humidityLow":73,"humidityAvg":77,"qcStatus":1,"metric":{"tempHigh":11,"tempLow":9,"tempAvg":10,"windspeedHigh":12,"windspeedLow":1,"windspeedAvg":6,"windgustHigh":17,"windgustLow":2,"windgustAvg":8,"dewptHigh":7,"dewptLow":6,"dewptAvg":7,"windchillHigh":11,"windchillLow":8,"windchillAvg":10,"heatindexHigh":11,"heatindexLow":9,"heatindexAvg":10,"pressureMax":1017.34,"pressureMin":1016.63,"pressureTrend":0.41,"precipRate":0.00,"precipTotal":0.00}},{"stationID":"ISTGBUCH2","tz":"Europe/London","obsTimeUtc":"2022-04-25T11:59:51Z","obsTimeLocal":"2022-04-25 12:59:51","epoch":1650887991,"lat":56.118,"lon":-4.301648,"solarRadiationHigh":605.56,"uvHigh":5.0,"winddirAvg":126,"humidityHigh":78,"humidityLow":67,"humidityAvg":72,"qcStatus":1,"metric":{"tempHigh":12,"tempLow":9,"tempAvg":11,"windspeedHigh":9,"windspeedLow":1,"windspeedAvg":5,"windgustHigh":11,"windgustLow":2,"windgustAvg":6,"dewptHigh":7,"dewptLow":5,"dewptAvg":6,"windchillHigh":12,"windchillLow":9,"windchillAvg":11,"heatindexHigh":12,"heatindexLow":9,"heatindexAvg":11,"pressureMax":1017.34,"pressureMin":1016.83,"pressureTrend":0.10,"precipRate":0.00,"precipTotal":0.00}},{"stationID":"ISTGBUCH2","tz":"Europe/London","obsTimeUtc":"2022-04-25T12:59:51Z","obsTimeLocal":"2022-04-25 13:59:51","epoch":1650891591,"lat":56.118,"lon":-4.301648,"solarRadiationHigh":814.27,"uvHigh":7.0,"winddirAvg":132,"humidityHigh":77,"humidityLow":68,"humidityAvg":73,"qcStatus":1,"metric":{"tempHigh":12,"tempLow":11,"tempAvg":11,"windspeedHigh":9,"windspeedLow":0,"windspeedAvg":4,"windgustHigh":11,"windgustLow":2,"windgustAvg":6,"dewptHigh":7,"dewptLow":6,"dewptAvg":7,"windchillHigh":12,"windchillLow":11,"windchillAvg":11,"heatindexHigh":12,"heatindexLow":11,"heatindexAvg":11,"pressureMax":1017.44,"pressureMin":1016.83,"pressureTrend":0.00,"precipRate":0.00,"precipTotal":0.00}},{"stationID":"ISTGBUCH2","tz":"Europe/London","obsTimeUtc":"2022-04-25T13:59:51Z","obsTimeLocal":"2022-04-25 14:59:51","epoch":1650895191,"lat":56.118,"lon":-4.301648,"solarRadiationHigh":902.72,"uvHigh":8.0,"winddirAvg":118,"humidityHigh":76,"humidityLow":65,"humidityAvg":70,"qcStatus":1,"metric":{"tempHigh":12,"tempLow":11,"tempAvg":12,"windspeedHigh":8,"windspeedLow":1,"windspeedAvg":4,"windgustHigh":13,"windgustLow":2,"windgustAvg":6,"dewptHigh":8,"dewptLow":6,"dewptAvg":7,"windchillHigh":12,"windchillLow":11,"windchillAvg":12,"heatindexHigh":12,"heatindexLow":11,"heatindexAvg":12,"pressureMax":1017.61,"pressureMin":1017.14,"pressureTrend":0.00,"precipRate":0.00,"precipTotal":0.00}},{"stationID":"ISTGBUCH2","tz":"Europe/London","obsTimeUtc":"2022-04-25T14:59:51Z","obsTimeLocal":"2022-04-25 15:59:51","epoch":1650898791,"lat":56.118,"lon":-4.301648,"solarRadiationHigh":339.61,"uvHigh":3.0,"winddirAvg":102,"humidityHigh":74,"humidityLow":60,"humidityAvg":66,"qcStatus":1,"metric":{"tempHigh":13,"tempLow":11,"tempAvg":12,"windspeedHigh":9,"windspeedLow":0,"windspeedAvg":5,"windgustHigh":13,"windgustLow":0,"windgustAvg":6,"dewptHigh":7,"dewptLow":5,"dewptAvg":6,"windchillHigh":13,"windchillLow":11,"windchillAvg":12,"heatindexHigh":13,"heatindexLow":11,"heatindexAvg":12,"pressureMax":1017.44,"pressureMin":1017.03,"pressureTrend":0.00,"precipRate":0.00,"precipTotal":0.00}},{"stationID":"ISTGBUCH2","tz":"Europe/London","obsTimeUtc":"2022-04-25T15:59:51Z","obsTimeLocal":"2022-04-25 16:59:51","epoch":1650902391,"lat":56.118,"lon":-4.301648,"solarRadiationHigh":516.99,"uvHigh":5.0,"winddirAvg":110,"humidityHigh":66,"humidityLow":53,"humidityAvg":60,"qcStatus":1,"metric":{"tempHigh":14,"tempLow":12,"tempAvg":13,"windspeedHigh":10,"windspeedLow":1,"windspeedAvg":4,"windgustHigh":15,"windgustLow":2,"windgustAvg":6,"dewptHigh":7,"dewptLow":4,"dewptAvg":5,"windchillHigh":14,"windchillLow":12,"windchillAvg":13,"heatindexHigh":14,"heatindexLow":12,"heatindexAvg":13,"pressureMax":1017.54,"pressureMin":1016.93,"pressureTrend":-0.20,"precipRate":0.00,"precipTotal":0.00}},{"stationID":"ISTGBUCH2","tz":"Europe/London","obsTimeUtc":"2022-04-25T16:59:51Z","obsTimeLocal":"2022-04-25 17:59:51","epoch":1650905991,"lat":56.118,"lon":-4.301648,"solarRadiationHigh":360.89,"uvHigh":3.0,"winddirAvg":105,"humidityHigh":67,"humidityLow":58,"humidityAvg":61,"qcStatus":1,"metric":{"tempHigh":13,"tempLow":12,"tempAvg":12,"windspeedHigh":8,"windspeedLow":0,"windspeedAvg":4,"windgustHigh":9,"windgustLow":0,"windgustAvg":5,"dewptHigh":6,"dewptLow":4,"dewptAvg":5,"windchillHigh":13,"windchillLow":12,"windchillAvg":12,"heatindexHigh":13,"heatindexLow":12,"heatindexAvg":12,"pressureMax":1017.24,"pressureMin":1016.83,"pressureTrend":-0.10,"precipRate":0.00,"precipTotal":0.00}},{"stationID":"ISTGBUCH2","tz":"Europe/London","obsTimeUtc":"2022-04-25T17:59:51Z","obsTimeLocal":"2022-04-25 18:59:51","epoch":1650909591,"lat":56.118,"lon":-4.301648,"solarRadiationHigh":253.24,"uvHigh":2.0,"winddirAvg":112,"humidityHigh":69,"humidityLow":57,"humidityAvg":63,"qcStatus":1,"metric":{"tempHigh":13,"tempLow":11,"tempAvg":12,"windspeedHigh":8,"windspeedLow":0,"windspeedAvg":3,"windgustHigh":9,"windgustLow":0,"windgustAvg":4,"dewptHigh":7,"dewptLow":4,"dewptAvg":5,"windchillHigh":13,"windchillLow":11,"windchillAvg":12,"heatindexHigh":13,"heatindexLow":11,"heatindexAvg":12,"pressureMax":1017.44,"pressureMin":1016.83,"pressureTrend":0.10,"precipRate":0.00,"precipTotal":0.00}},{"stationID":"ISTGBUCH2","tz":"Europe/London","obsTimeUtc":"2022-04-25T18:59:51Z","obsTimeLocal":"2022-04-25 19:59:51","epoch":1650913191,"lat":56.118,"lon":-4.301648,"solarRadiationHigh":98.36,"uvHigh":0.0,"winddirAvg":110,"humidityHigh":71,"humidityLow":62,"humidityAvg":67,"qcStatus":1,"metric":{"tempHigh":11,"tempLow":10,"tempAvg":10,"windspeedHigh":6,"windspeedLow":0,"windspeedAvg":2,"windgustHigh":7,"windgustLow":0,"windgustAvg":2,"dewptHigh":6,"dewptLow":4,"dewptAvg":5,"windchillHigh":11,"windchillLow":10,"windchillAvg":10,"heatindexHigh":11,"heatindexLow":10,"heatindexAvg":10,"pressureMax":1017.71,"pressureMin":1017.03,"pressureTrend":0.58,"precipRate":0.00,"precipTotal":0.00}},{"stationID":"ISTGBUCH2","tz":"Europe/London","obsTimeUtc":"2022-04-25T19:59:51Z","obsTimeLocal":"2022-04-25 20:59:51","epoch":1650916791,"lat":56.118,"lon":-4.301648,"solarRadiationHigh":21.16,"uvHigh":0.0,"winddirAvg":78,"humidityHigh":81,"humidityLow":67,"humidityAvg":71,"qcStatus":0,"metric":{"tempHigh":10,"tempLow":6,"tempAvg":8,"windspeedHigh":3,"windspeedLow":0,"windspeedAvg":1,"windgustHigh":4,"windgustLow":0,"windgustAvg":1,"dewptHigh":4,"dewptLow":3,"dewptAvg":4,"windchillHigh":10,"windchillLow":6,"windchillAvg":8,"heatindexHigh":10,"heatindexLow":6,"heatindexAvg":8,"pressureMax":1018.12,"pressureMin":1017.44,"pressureTrend":0.51,"precipRate":0.00,"precipTotal":0.00}},{"stationID":"ISTGBUCH2","tz":"Europe/London","obsTimeUtc":"2022-04-25T20:59:51Z","obsTimeLocal":"2022-04-25 21:59:51","epoch":1650920391,"lat":56.118,"lon":-4.301648,"solarRadiationHigh":0.00,"uvHigh":0.0,"winddirAvg":41,"humidityHigh":82,"humidityLow":78,"humidityAvg":80,"qcStatus":1,"metric":{"tempHigh":7,"tempLow":6,"tempAvg":6,"windspeedHigh":2,"windspeedLow":0,"windspeedAvg":0,"windgustHigh":2,"windgustLow":0,"windgustAvg":0,"dewptHigh":3,"dewptLow":3,"dewptAvg":3,"windchillHigh":7,"windchillLow":6,"windchillAvg":6,"heatindexHigh":7,"heatindexLow":6,"heatindexAvg":6,"pressureMax":1018.52,"pressureMin":1017.81,"pressureTrend":0.41,"precipRate":0.00,"precipTotal":0.00}},{"stationID":"ISTGBUCH2","tz":"Europe/London","obsTimeUtc":"2022-04-25T21:59:51Z","obsTimeLocal":"2022-04-25 22:59:51","epoch":1650923991,"lat":56.118,"lon":-4.301648,"solarRadiationHigh":0.00,"uvHigh":0.0,"winddirAvg":330,"humidityHigh":84,"humidityLow":81,"humidityAvg":83,"qcStatus":1,"metric":{"tempHigh":7,"tempLow":6,"tempAvg":7,"windspeedHigh":0,"windspeedLow":0,"windspeedAvg":0,"windgustHigh":0,"windgustLow":0,"windgustAvg":0,"dewptHigh":4,"dewptLow":3,"dewptAvg":4,"windchillHigh":7,"windchillLow":6,"windchillAvg":7,"heatindexHigh":7,"heatindexLow":6,"heatindexAvg":7,"pressureMax":1019.03,"pressureMin":1018.32,"pressureTrend":0.31,"precipRate":0.00,"precipTotal":0.00}},{"stationID":"ISTGBUCH2","tz":"Europe/London","obsTimeUtc":"2022-04-25T22:59:51Z","obsTimeLocal":"2022-04-25 23:59:51","epoch":1650927591,"lat":56.118,"lon":-4.301648,"solarRadiationHigh":0.00,"uvHigh":0.0,"winddirAvg":17,"humidityHigh":86,"humidityLow":85,"humidityAvg":85,"qcStatus":1,"metric":{"tempHigh":7,"tempLow":6,"tempAvg":7,"windspeedHigh":1,"windspeedLow":0,"windspeedAvg":0,"windgustHigh":2,"windgustLow":0,"windgustAvg":0,"dewptHigh":5,"dewptLow":4,"dewptAvg":4,"windchillHigh":7,"windchillLow":6,"windchillAvg":7,"heatindexHigh":7,"heatindexLow":6,"heatindexAvg":7,"pressureMax":1019.44,"pressureMin":1018.73,"pressureTrend":0.31,"precipRate":0.00,"precipTotal":0.00}}]}
